.gitignore
CHANGES.rst
LICENCE.GPL
LICENCE.rst
MANIFEST.in
README.rst
bootstrap-buildout.py
buildout.cfg
setup.cfg
setup.py
fourdigits/__init__.py
fourdigits.seo.egg-info/PKG-INFO
fourdigits.seo.egg-info/SOURCES.txt
fourdigits.seo.egg-info/dependency_links.txt
fourdigits.seo.egg-info/entry_points.txt
fourdigits.seo.egg-info/namespace_packages.txt
fourdigits.seo.egg-info/not-zip-safe
fourdigits.seo.egg-info/paster_plugins.txt
fourdigits.seo.egg-info/requires.txt
fourdigits.seo.egg-info/top_level.txt
fourdigits/seo/__init__.py
fourdigits/seo/configure.zcml
fourdigits/seo/interfaces.py
fourdigits/seo/synci18n.sh
fourdigits/seo/tests.py
fourdigits/seo/upgrades.py
fourdigits/seo/upgrades.zcml
fourdigits/seo/behaviors/__init__.py
fourdigits/seo/behaviors/canonical.py
fourdigits/seo/behaviors/configure.zcml
fourdigits/seo/behaviors/image.py
fourdigits/seo/behaviors/multilanguage.py
fourdigits/seo/behaviors/seo.py
fourdigits/seo/browser/__init__.py
fourdigits/seo/browser/configure.zcml
fourdigits/seo/browser/settings.py
fourdigits/seo/browser/viewlets.py
fourdigits/seo/browser/views.py
fourdigits/seo/browser/templates/author.pt
fourdigits/seo/browser/templates/dublin_core.pt
fourdigits/seo/browser/templates/favicon.pt
fourdigits/seo/browser/templates/multilanguage.pt
fourdigits/seo/browser/templates/path_bar.pt
fourdigits/seo/browser/templates/portal_header.pt
fourdigits/seo/browser/templates/robots.pt
fourdigits/seo/browser/templates/sections.pt
fourdigits/seo/browser/templates/sitemap-image.pt
fourdigits/seo/browser/templates/sitemap.pt
fourdigits/seo/locales/README.txt
fourdigits/seo/locales/fourdigits.seo.pot
fourdigits/seo/locales/NL/LC_MESSAGES/README.txt
fourdigits/seo/locales/NL/LC_MESSAGES/fourdigits.seo.po
fourdigits/seo/overrides/__init__.py
fourdigits/seo/overrides/configure.zcml
fourdigits/seo/overrides/userdata.py
fourdigits/seo/profiles/default/browserlayer.xml
fourdigits/seo/profiles/default/componentregistry.xml
fourdigits/seo/profiles/default/controlpanel.xml
fourdigits/seo/profiles/default/jsregistry.xml
fourdigits/seo/profiles/default/memberdata_properties.xml
fourdigits/seo/profiles/default/metadata.xml
fourdigits/seo/profiles/default/propertiestool.xml
fourdigits/seo/profiles/default/registry.xml
fourdigits/seo/profiles/default/skins.xml
fourdigits/seo/profiles/default/types/Collection.xml
