Metadata-Version: 1.1
Name: fourdigits.seo
Version: 1.0
Summary: Package for SEO
Home-page: http://www.fourdigits.nl
Author: Four Digits
Author-email: info@fourdigits.nl
License: GPL version 2
Platform: UNKNOWN
Classifier: Framework :: Plone
Classifier: Programming Language :: Python
